{
  "veggies": [
    {
      "id": 1,
      "name": "Carrot",
      "stock": 20,
      "price": 1.5
    },
    {
      "id": 2,
      "name": "Potato",
      "stock": 30,
      "price": 0.8
    },
    {
      "id": 3,
      "name": "Spinach",
      "stock": 30,
      "price": 2.0
    },
    {
      "id": 4,
      "name": "Lettuce",
      "stock": 25,
      "price": 1.2
    },
    {
      "id": 5,
      "name": "Pepper",
      "stock": 18,
      "price": 1.8
    }
  ],
  "fruits": [
    {
      "id": 1,
      "name": "Apple",
      "stock": 25,
      "price": 1.0
    },
    {
      "id": 2,
      "name": "Banana",
      "stock": 18,
      "price": 0.6
    },
    {
      "id": 3,
      "name": "Orange",
      "stock": 35,
      "price": 1.2
    },
    {
      "id": 4,
      "name": "Grape",
      "stock": 22,
      "price": 2.5
    },
    {
      "id": 5,
      "name": "Strawberry",
      "stock": 28,
      "price": 3.0
    }
  ],
  "meats": [
    {
      "id": 1,
      "name": "Beef",
      "stock": 15,
      "price": 8.0
    },
    {
      "id": 2,
      "name": "Chicken",
      "stock": 25,
      "price": 5.0
    },
    {
      "id": 3,
      "name": "Lamb",
      "stock": 12,
      "price": 12.0
    },
    {
      "id": 4,
      "name": "Pork",
      "stock": 20,
      "price": 6.5
    },
    {
      "id": 5,
      "name": "Turkey",
      "stock": 18,
      "price": 7.0
    }
  ],
  "cheeses": [
    {
      "id": 1,
      "name": "Cheddar",
      "stock": 10,
      "price": 4.0
    },
    {
      "id": 2,
      "name": "Mozzarella",
      "stock": 14,
      "price": 3.5
    },
    {
      "id": 3,
      "name": "Parmesan",
      "stock": 8,
      "price": 5.5
    },
    {
      "id": 4,
      "name": "Swiss",
      "stock": 12,
      "price": 4.5
    },
    {
      "id": 5,
      "name": "Gouda",
      "stock": 9,
      "price": 4.2
    }
  ],
  "tomatoes": [
    {
      "id": 1,
      "name": "Cherry Tomato",
      "stock": 40,
      "price": 2.0
    },
    {
      "id": 2,
      "name": "Beefsteak Tomato",
      "stock": 30,
      "price": 1.8
    },
    {
      "id": 3,
      "name": "Roma Tomato",
      "stock": 20,
      "price": 1.5
    },
    {
      "id": 4,
      "name": "Heirloom Tomato",
      "stock": 15,
      "price": 2.5
    },
    {
      "id": 5,
      "name": "Grape Tomato",
      "stock": 25,
      "price": 2.2
    }
  ]
}
